vto_time/__init__.py
vto_time/admin.py
vto_time/apps.py
vto_time/models.py
vto_time/seed.json
vto_time/urls.py
vto_time/views.py
vto_time/migrations/0001_initial.py
vto_time/migrations/__init__.py
vto_time/templates/time/tz_list.dtl
vto_time-0.0.8.dist-info/METADATA
vto_time-0.0.8.dist-info/WHEEL
vto_time-0.0.8.dist-info/licenses/LICENSE
vto_time-0.0.8.dist-info/RECORD
