Metadata-Version: 2.4
Name: vto-time
Version: 0.0.8
Summary: This is a custom reusable Django time zones app.
Project-URL: Repository, https://github.com/venteto/vto-time
License-Expression: MIT
License-File: LICENSE
Requires-Python: >=3.13
